[{"id":90000015,"lat":47.636,"lng":6.838,"addr":"56, AVENUE DU GENERAL LECLERC","city":"BELFORT","cp":"90000","fuels":{"Gazole":{"p":1.905,"d":"2026-03-05"},"E10":{"p":1.735,"d":"2026-03-05"},"SP98":{"p":1.845,"d":"2026-03-05"}}},{"id":90500001,"lat":47.48973,"lng":6.92225,"addr":"37 Rue Alfred Péchin","city":"Beaucourt","cp":"90500","fuels":{"Gazole":{"p":1.89,"d":"2026-03-03"},"SP95":{"p":1.94,"d":"2026-03-03"},"SP98":{"p":1.99,"d":"2026-03-03"}}},{"id":90008001,"lat":47.628463633382005,"lng":6.8616609623314995,"addr":"1 avenue du général de Gaulle","city":"Belfort","cp":"90000","fuels":{"Gazole":{"p":1.855,"d":"2026-03-05"},"SP95":{"p":1.737,"d":"2026-03-05"},"E85":{"p":0.777,"d":"2026-03-05"},"E10":{"p":1.696,"d":"2026-03-05"},"SP98":{"p":1.821,"d":"2026-03-05"}}},{"id":90500002,"lat":47.49,"lng":6.922,"addr":"Rue Alfred Péchin","city":"BEAUCOURT","cp":"90500","fuels":{"Gazole":{"p":1.865,"d":"2026-03-04"},"SP95":{"p":1.843,"d":"2026-03-04"},"E10":{"p":1.779,"d":"2026-03-04"},"SP98":{"p":1.865,"d":"2026-03-04"}}},{"id":90000009,"lat":47.636,"lng":6.873,"addr":"57 Avenue d'Altkirch","city":"Belfort","cp":"90000","fuels":{"Gazole":{"p":1.889,"d":"2026-03-03"},"SP95":{"p":1.949,"d":"2026-03-03"},"E85":{"p":0.919,"d":"2026-03-03"},"SP98":{"p":1.979,"d":"2026-03-03"}}},{"id":90100004,"lat":47.511,"lng":7.001,"addr":"62 faubourg de Belfort","city":"Delle","cp":"90100","fuels":{"Gazole":{"p":1.969,"d":"2026-03-04"},"SP95":{"p":1.949,"d":"2026-03-03"},"GPLc":{"p":1.09,"d":"2026-03-03"},"SP98":{"p":1.979,"d":"2026-03-03"}}},{"id":90300002,"lat":47.66862601099999,"lng":6.842203087160001,"addr":"30, rue de Turenne","city":"VALDOIE","cp":"90300","fuels":{"Gazole":{"p":1.833,"d":"2026-03-03"},"SP95":{"p":1.799,"d":"2026-03-03"},"GPLc":{"p":0.989,"d":"2026-03-03"},"SP98":{"p":1.834,"d":"2026-03-03"}}},{"id":90100003,"lat":47.512,"lng":6.999,"addr":"37 FAUBOURG DE BELFORT","city":"DELLE","cp":"90100","fuels":{"Gazole":{"p":1.871,"d":"2026-03-04"},"E85":{"p":0.758,"d":"2026-03-04"},"E10":{"p":1.722,"d":"2026-03-04"},"SP98":{"p":1.828,"d":"2026-03-04"}}},{"id":90150001,"lat":47.688,"lng":6.955,"addr":"Rue de la baume, RD83","city":"MENONCOURT","cp":"90150","fuels":{"Gazole":{"p":1.99,"d":"2026-03-04"},"E10":{"p":1.845,"d":"2026-03-04"},"SP98":{"p":1.955,"d":"2026-03-04"}}},{"id":90200003,"lat":47.735,"lng":6.83,"addr":"72 Faubourg de Belfort","city":"GIROMAGNY","cp":"90200","fuels":{"Gazole":{"p":1.99,"d":"2026-03-04"},"E10":{"p":1.842,"d":"2026-03-04"},"SP98":{"p":1.952,"d":"2026-03-04"}}},{"id":90000014,"lat":47.626,"lng":6.86,"addr":"3 rue de Besançon","city":"BELFORT","cp":"90000","fuels":{"Gazole":{"p":1.905,"d":"2026-03-05"},"E85":{"p":0.799,"d":"2026-03-05"},"E10":{"p":1.735,"d":"2026-03-05"}}},{"id":90400001,"lat":47.6,"lng":6.862,"addr":"Route de montbéliard","city":"ANDELNANS","cp":"90400","fuels":{"Gazole":{"p":1.856,"d":"2026-03-04"},"E85":{"p":0.777,"d":"2026-03-02"},"E10":{"p":1.697,"d":"2026-03-04"},"SP98":{"p":1.822,"d":"2026-03-04"}}},{"id":90160001,"lat":47.641,"lng":6.916,"addr":"CD 419","city":"BESSONCOURT","cp":"90160","fuels":{"Gazole":{"p":1.856,"d":"2026-03-04"},"GPLc":{"p":0.959,"d":"2026-03-04"},"E10":{"p":1.703,"d":"2026-03-04"},"SP98":{"p":1.822,"d":"2026-03-04"}}},{"id":90200002,"lat":47.7374160601,"lng":6.8362603018,"addr":"ZAC du Mont Jean, faubourg d' alsace","city":"GIROMAGNY","cp":"90200","fuels":{"Gazole":{"p":1.789,"d":"2026-03-03"},"SP95":{"p":1.795,"d":"2026-03-03"},"SP98":{"p":1.819,"d":"2026-03-03"}}},{"id":90000002,"lat":47.64,"lng":6.868,"addr":"4 Faubourg de Brisach","city":"Belfort","cp":"90000","fuels":{"Gazole":{"p":1.999,"d":"2026-03-04"},"E10":{"p":1.839,"d":"2026-03-04"},"SP98":{"p":1.949,"d":"2026-03-04"}}},{"id":90000013,"lat":47.631,"lng":6.867,"addr":"AVENUE D'ALTKIRCH","city":"BELFORT","cp":"90000","fuels":{"Gazole":{"p":1.99,"d":"2026-03-05"},"E85":{"p":0.809,"d":"2026-03-05"},"GPLc":{"p":0.955,"d":"2026-03-05"},"E10":{"p":1.824,"d":"2026-03-05"},"SP98":{"p":1.934,"d":"2026-03-05"}}}]